turbobt-0.3.1.dist-info/METADATA
turbobt-0.3.1.dist-info/WHEEL
turbobt-0.3.1.dist-info/entry_points.txt
turbobt-0.3.1.dist-info/licenses/LICENSE
turbobt/__init__.py
turbobt/batch.py
turbobt/block.py
turbobt/client.py
turbobt/neuron.py
turbobt/subnet.py
turbobt/substrate/__init__.py
turbobt/substrate/_hashers.py
turbobt/substrate/_models.py
turbobt/substrate/_scalecodec.py
turbobt/substrate/client.py
turbobt/substrate/exceptions.py
turbobt/substrate/extrinsic.py
turbobt/substrate/pallets/__init__.py
turbobt/substrate/pallets/_base.py
turbobt/substrate/pallets/_types.py
turbobt/substrate/pallets/author.py
turbobt/substrate/pallets/chain.py
turbobt/substrate/pallets/state.py
turbobt/substrate/pallets/system.py
turbobt/substrate/pallets/timestamp.py
turbobt/substrate/pallets/utility.py
turbobt/substrate/runtime/__init__.py
turbobt/substrate/runtime/_base.py
turbobt/substrate/runtime/metadata.py
turbobt/substrate/transports/__init__.py
turbobt/substrate/transports/base.py
turbobt/substrate/transports/http.py
turbobt/substrate/transports/websocket.py
turbobt/subtensor/__init__.py
turbobt/subtensor/cache.py
turbobt/subtensor/client.py
turbobt/subtensor/exceptions.py
turbobt/subtensor/pallets/__init__.py
turbobt/subtensor/pallets/_base.py
turbobt/subtensor/pallets/_types.py
turbobt/subtensor/pallets/admin_utils.py
turbobt/subtensor/pallets/commitments.py
turbobt/subtensor/pallets/subtensor_module.py
turbobt/subtensor/pallets/sudo.py
turbobt/subtensor/runtime/__init__.py
turbobt/subtensor/runtime/_base.py
turbobt/subtensor/runtime/neuron_info.py
turbobt/subtensor/runtime/subnet_info.py
turbobt/subtensor/types.py
turbobt-0.3.1.dist-info/RECORD
