Metadata-Version: 2.4
Name: turbobt
Version: 0.3.1
Summary: A next generation Bittensor SDK, for Python 3.
Author-Email: Reef Technologies <opensource@reef.pl>
License-Expression: BSD-3-Clause
License-File: LICENSE
Classifier: Development Status :: 2 - Pre-Alpha
Classifier: Framework :: AsyncIO
Classifier: Operating System :: OS Independent
Classifier: Programming Language :: Python :: 3 :: Only
Classifier: Programming Language :: Python :: 3
Classifier: Programming Language :: Python :: 3.11
Classifier: Programming Language :: Python :: 3.12
Classifier: Programming Language :: Python :: 3.13
Project-URL: Homepage, https://github.com/bactensor/turbobt
Project-URL: Issues, https://github.com/bactensor/turbobt/issues
Requires-Python: >=3.11
Requires-Dist: bittensor-drand~=1.0.0
Requires-Dist: bittensor-wallet~=4.0.0
Requires-Dist: eciespy~=0.4.6
Requires-Dist: httpx~=0.26.0
Requires-Dist: scalecodec~=1.2.11
Requires-Dist: websockets~=14.1
Requires-Dist: xxhash~=3.5.0
